{"timestamp":1697719667614,"hash":"c4937801184ad427b7c714aa8648eed6","assets":{"/dacia/":{"/fonts/Poppins-Regular.woff2":true,"/fonts/Poppins-SemiBold.woff2":true,"/fonts/Poppins-Medium.woff2":true,"/fonts/Poppins-Light.woff2":true,"/fonts/Poppins-Bold.woff2":true},"/kia-sportage/":{"/fonts/Poppins-SemiBold.woff2":true,"/fonts/Poppins-Regular.woff2":true,"/fonts/Poppins-Medium.woff2":true,"/fonts/Poppins-Bold.woff2":true,"/fonts/Poppins-Light.woff2":true},"/renaut-koleos/":{"/fonts/Poppins-SemiBold.woff2":true,"/fonts/Poppins-Regular.woff2":true,"/fonts/Poppins-Medium.woff2":true,"/fonts/Poppins-Bold.woff2":true,"/fonts/Poppins-Light.woff2":true},"/tesla-model-s/":{"/fonts/Poppins-SemiBold.woff2":true,"/fonts/Poppins-Regular.woff2":true,"/fonts/Poppins-Medium.woff2":true,"/fonts/Poppins-Light.woff2":true,"/fonts/Poppins-Bold.woff2":true},"/subaru-forester/":{"/fonts/Poppins-SemiBold.woff2":true,"/fonts/Poppins-Regular.woff2":true,"/fonts/Poppins-Medium.woff2":true,"/fonts/Poppins-Light.woff2":true,"/fonts/Poppins-Bold.woff2":true},"/jeep-grand-cherokee/":{"/fonts/Poppins-SemiBold.woff2":true,"/fonts/Poppins-Regular.woff2":true,"/fonts/Poppins-Medium.woff2":true,"/fonts/Poppins-Light.woff2":true,"/fonts/Poppins-Bold.woff2":true},"/mercedes-benz-cla200/":{"/fonts/Poppins-SemiBold.woff2":true,"/fonts/Poppins-Regular.woff2":true,"/fonts/Poppins-Medium.woff2":true,"/fonts/Poppins-Light.woff2":true,"/fonts/Poppins-Bold.woff2":true},"/audi-a5/":{"/fonts/Poppins-SemiBold.woff2":true,"/fonts/Poppins-Regular.woff2":true,"/fonts/Poppins-Medium.woff2":true,"/fonts/Poppins-Light.woff2":true,"/fonts/Poppins-Bold.woff2":true},"/test-post/":{"/fonts/Poppins-SemiBold.woff2":true,"/fonts/Poppins-Medium.woff2":true,"/fonts/Poppins-Regular.woff2":true,"/fonts/Poppins-Bold.woff2":true},"/ka-drosi-nopirkt-auto/":{"/fonts/Poppins-SemiBold.woff2":true,"/fonts/Poppins-Medium.woff2":true,"/fonts/Poppins-Regular.woff2":true,"/fonts/Poppins-Bold.woff2":true},"/test-post2/":{"/fonts/Poppins-SemiBold.woff2":true,"/fonts/Poppins-Medium.woff2":true,"/fonts/Poppins-Regular.woff2":true,"/fonts/Poppins-Bold.woff2":true},"/hello-world/":{"/fonts/Poppins-SemiBold.woff2":true,"/fonts/Poppins-Medium.woff2":true,"/fonts/Poppins-Regular.woff2":true,"/fonts/Poppins-Bold.woff2":true},"/autorazotaji-atsakas-no-dizeldzinejiem-kas-tos-aizstas/":{"/fonts/Poppins-SemiBold.woff2":true,"/fonts/Poppins-Medium.woff2":true,"/fonts/Poppins-Regular.woff2":true,"/fonts/Poppins-Bold.woff2":true},"/dev-404-page/":{"/fonts/Poppins-Medium.woff2":true,"/fonts/Poppins-Regular.woff2":true,"/fonts/Poppins-Bold.woff2":true},"/404/":{"/fonts/Poppins-SemiBold.woff2":true,"/fonts/Poppins-Bold.woff2":true,"/fonts/Poppins-Regular.woff2":true},"/404.html":{"/fonts/Poppins-SemiBold.woff2":true,"/fonts/Poppins-Bold.woff2":true,"/fonts/Poppins-Regular.woff2":true},"/about/":{"/fonts/Poppins-SemiBold.woff2":true,"/fonts/Poppins-Bold.woff2":true,"/fonts/Poppins-Regular.woff2":true},"/blog/":{"/fonts/Poppins-SemiBold.woff2":true,"/fonts/Poppins-Bold.woff2":true,"/fonts/Poppins-Regular.woff2":true,"/fonts/Poppins-Medium.woff2":true},"/contact/":{"/fonts/Poppins-SemiBold.woff2":true,"/fonts/Poppins-Bold.woff2":true,"/fonts/Poppins-Regular.woff2":true},"/":{"/fonts/Poppins-SemiBold.woff2":true,"/fonts/Poppins-Regular.woff2":true,"/fonts/Poppins-Bold.woff2":true,"/fonts/Poppins-Medium.woff2":true,"/fonts/Poppins-Light.woff2":true},"/shop/":{"/fonts/Poppins-SemiBold.woff2":true,"/fonts/Poppins-Regular.woff2":true,"/fonts/Poppins-Bold.woff2":true,"/fonts/Poppins-Medium.woff2":true,"/fonts/Poppins-Light.woff2":true}}}